ohre/__init__.py
ohre/abc_analyzer/oh_abcbuf.py
ohre/core/oh_app.py
ohre/core/oh_common.py
ohre/core/oh_hap.py
ohre/misc/Log.py
ohre/res_analyzer/oh_resbuf.py
ohre/rules/IP.yar
ohre/rules/filters_filename.py
ohre-0.0.2a0.dist-info/LICENSE
ohre-0.0.2a0.dist-info/METADATA
ohre-0.0.2a0.dist-info/WHEEL
ohre-0.0.2a0.dist-info/RECORD
