Metadata-Version: 2.1
Name: ohre
Version: 0.0.2a0
Summary: ohre is a analyze and reverse tool of HarmonyOS APP package.
Home-page: https://github.com/ohreteam
License: AGPL-3.0
Author: koki
Author-email: k0k1fish@outlook.com
Requires-Python: >=3.9,<4.0
Classifier: Development Status :: 3 - Alpha
Classifier: License :: OSI Approved :: GNU Affero General Public License v3
Classifier: License :: OSI Approved :: GNU Lesser General Public License v3 (LGPLv3)
Classifier: Operating System :: OS Independent
Classifier: Programming Language :: Python
Classifier: Programming Language :: Python :: 3
Classifier: Programming Language :: Python :: 3.9
Classifier: Programming Language :: Python :: 3.10
Classifier: Programming Language :: Python :: 3.11
Classifier: Programming Language :: Python :: 3.12
Classifier: Programming Language :: Python :: 3.13
Classifier: Programming Language :: Python :: 3 :: Only
Classifier: Topic :: Security
Classifier: Topic :: Software Development
Classifier: Topic :: Utilities
Requires-Dist: pendulum (>=3.0.0,<4.0.0)
Requires-Dist: yara-python (>=4.5.0,<5.0.0)
Project-URL: Documentation, https://github.com/ohreteam/ohre
